testpackagemds/__init__.py
testpackagemds/testpackagemds.py
testpackagemds-1.0.0.dist-info/LICENSE
testpackagemds-1.0.0.dist-info/WHEEL
testpackagemds-1.0.0.dist-info/METADATA
testpackagemds-1.0.0.dist-info/RECORD
